newsworthycharts/__init__.py
newsworthycharts/bubblemap.py
newsworthycharts/categoricalchart.py
newsworthycharts/chart.py
newsworthycharts/choroplethmap.py
newsworthycharts/datawrapper.py
newsworthycharts/map.py
newsworthycharts/rangeplot.py
newsworthycharts/rankchart.py
newsworthycharts/scatterplot.py
newsworthycharts/seasonalchart.py
newsworthycharts/serialchart.py
newsworthycharts/storage.py
newsworthycharts/stripechart.py
newsworthycharts/custom/__init__.py
newsworthycharts/custom/climate_cars.py
newsworthycharts/lib/__init__.py
newsworthycharts/lib/color_fn.py
newsworthycharts/lib/colors.py
newsworthycharts/lib/datalist.py
newsworthycharts/lib/formatter.py
newsworthycharts/lib/geography.py
newsworthycharts/lib/locator.py
newsworthycharts/lib/mimetypes.py
newsworthycharts/lib/utils.py
newsworthycharts/maps/se-4.gpkg
newsworthycharts/maps/se-7.gpkg
newsworthycharts/rc/newsworthy
newsworthycharts/translations/datawrapper_regions.csv
newsworthycharts/translations/regions.py
newsworthycharts/translations/se_municipalities.csv
newsworthycharts-1.78.3.dist-info/licenses/LICENSE.txt
newsworthycharts-1.78.3.dist-info/METADATA
newsworthycharts-1.78.3.dist-info/WHEEL
newsworthycharts-1.78.3.dist-info/top_level.txt
newsworthycharts-1.78.3.dist-info/RECORD
