Metadata-Version: 2.4
Name: newsworthycharts
Version: 1.78.3
Summary: Matplotlib wrapper to create charts and publish them on Amazon S3
Home-page: https://github.com/jplusplus/newsworthycharts
Download-URL: https://github.com/jplusplus/newsworthycharts/archive/1.78.3.tar.gz
Author: Jens Finnäs and Leo Wallentin, J++ Stockholm
Author-email: stockholm@jplusplus.org
License: MIT
Requires-Python: >=3.10
License-File: LICENSE.txt
Requires-Dist: boto3>=1.26
Requires-Dist: matplotlib==3.10.8
Requires-Dist: langcodes>=3.3
Requires-Dist: Babel<3,>=2.14.0
Requires-Dist: PyYAML>=3
Requires-Dist: adjustText==1.3.0
Requires-Dist: numpy>2
Requires-Dist: python-dateutil<3,>=2
Requires-Dist: Pillow==12.0.0
Requires-Dist: requests>=2.22
Requires-Dist: matplotlib-label-lines==0.5.1
Requires-Dist: geopandas==1.1.1
Requires-Dist: mapclassify==2.10.0
Dynamic: author
Dynamic: author-email
Dynamic: description
Dynamic: description-content-type
Dynamic: download-url
Dynamic: home-page
Dynamic: license
Dynamic: license-file
Dynamic: requires-dist
Dynamic: requires-python
Dynamic: summary
